cv2_fit_text_in_box/LICENSE
cv2_fit_text_in_box/README.MD
cv2_fit_text_in_box/__init__.py
cv2_fit_text_in_box/requirements.txt
cv2_fit_text_in_box/thirdparty.json
cv2_fit_text_in_box-0.10.dist-info/LICENSE.rst
cv2_fit_text_in_box-0.10.dist-info/METADATA
cv2_fit_text_in_box-0.10.dist-info/WHEEL
cv2_fit_text_in_box-0.10.dist-info/top_level.txt
cv2_fit_text_in_box-0.10.dist-info/RECORD
