Metadata-Version: 2.1
Name: cv2-fit-text-in-box
Version: 0.10
Summary: Finds the best fitting text size for a bounding box
Home-page: https://github.com/hansalemaos/cv2_fit_text_in_box
Author: Johannes Fischer
Author-email: <aulasparticularesdealemaosp@gmail.com>
License: MIT
Keywords: cv2,text,box
Classifier: Development Status :: 4 - Beta
Classifier: Programming Language :: Python :: 3 :: Only
Classifier: Programming Language :: Python :: 3.9
Classifier: Topic :: Scientific/Engineering :: Visualization
Classifier: Topic :: Software Development :: Libraries :: Python Modules
Classifier: Topic :: Text Editors :: Text Processing
Classifier: Topic :: Text Processing :: General
Classifier: Topic :: Text Processing :: Indexing
Classifier: Topic :: Text Processing :: Filters
Classifier: Topic :: Utilities
License-File: LICENSE.rst
Requires-Dist: a-cv-imwrite-imread-plus
Requires-Dist: numpy
Requires-Dist: opencv-python
Requires-Dist: PILasOPENCV
Requires-Dist: Pillow
